BarrelShifter/Barrel_Shifter.v
// File: Barrel_Shifter.v
// Generated by MyHDL 0.11.45
// Date: Tue Jul 30 19:58:05 2024


`timescale 1ns/10ps

module Barrel_Shifter (
    par_in,
    par_out,
    shift_amount
);
// A barrel shifter with 3-bits shift amount for 12-bits register.
// :param par_in: Parallel input (12-bits).
// :param par_out: Parallel output (12-bits).
// :param shift_amount: Amount of shift to be executed (3-bits maximum).

input [11:0] par_in;
output [11:0] par_out;
wire [11:0] par_out;
input [2:0] shift_amount;





assign par_out = (par_in >>> shift_amount);

endmodule

BarrelShifter/Barrel_Shifter.vcd
$date
    Tue Jul 30 19:58:05 2024
$end
$version
    MyHDL 0.11.45
$end
$timescale
    1ns
$end

$scope module Barrel_Shifter $end
$var reg 12 ! par_out $end
$var reg 12 " par_in $end
$var reg 3 # shift_amount $end
$scope module Barrel_Shifter0 $end
$var reg 12 " par_in $end
$var reg 12 ! par_out $end
$var reg 3 # shift_amount $end
$upscope $end
$upscope $end

$enddefinitions $end
$dumpvars
b000000000000 !
b000000000000 "
b000 #
$end
b111101111000 "
b110 #
b000000111101 !
#10
b100001110000 "
b011 #
b000100001110 !
#20
b000100011100 "
b100 #
b000000010001 !
#30
b010100010100 "
b011 #
b000010100010 !
#40
b000001010011 "
b000 #
b000001010011 !
#50
b100100101011 "
b011 #
b000100100101 !
#60
b110101100101 "
b110 #
b000000110101 !
#70
b101100110010 "
b010 #
b001011001100 !
#80
b111001010000 "
b101 #
b000001110010 !
#90
b001010000100 "
b000 #
b001010000100 !
#100
b101001110111 "
b110 #
b000000101001 !
#110
b100010011101 "
b001 #
b010001001110 !
#120
b111001000110 "
b100 #
b000011100100 !
#130
b000110011111 "
b001 #
b000011001111 !
#140
b101011001110 "
b000 #
b101011001110 !
#150
b110111111001 "
b001 #
b011011111100 !
#160
b001010101001 "
b100 #
b000000101010 !
#170
b011000010111 "
b111 #
b000000001100 !
#180
b001000100001 "
b100 #
b000000100010 !
#190
b001010110100 "
b110 #
b000000001010 !
