Simple_Memory.v
// File: Simple_Memory.v
// Generated by MyHDL 0.11.45
// Date: Sun Apr 14 13:01:00 2024


`timescale 1ns/10ps

module Simple_Memory (
    clk,
    en,
    addr,
    din,
    dout
);
// This module represents a simple memory composed of 32 registers, each storing an 8-bit value.
// Parameters:
//     - clk: A clock signal that synchronizes the operations of the memory.
//     - en: A write enable signal, controlling whether data is written into the memory.
//     - addr: An address signal specifying the location to write data to or read data from.
//     - din: A data input signal carrying the information to be written into the memory.
//     - dout: A data output signal providing the data read from the memory.

input clk;
input en;
input [4:0] addr;
input [7:0] din;
output [7:0] dout;
wire [7:0] dout;

reg [7:0] mem [0:32-1];



always @(posedge clk) begin: SIMPLE_MEMORY_WRITE
    if (en) begin
        mem[addr] <= din;
    end
end



assign dout = mem[addr];

endmodule

Simple_Memory.vcd
$date
    Sun Apr 14 13:01:00 2024
$end
$version
    MyHDL 0.11.45
$end
$timescale
    1ns
$end

$scope module Simple_Memory $end
$var reg 8 ! dout $end
$var reg 5 " addr $end
$var reg 1 # clk $end
$var reg 8 $ din $end
$var reg 1 % en $end
$scope module Memory0 $end
$var reg 1 # clk $end
$var reg 1 % en $end
$var reg 5 " addr $end
$var reg 8 $ din $end
$var reg 8 ! dout $end
$scope module mem $end
$var reg 8 & mem(0) $end
$var reg 8 ' mem(1) $end
$var reg 8 ( mem(2) $end
$var reg 8 ) mem(3) $end
$var reg 8 * mem(4) $end
$var reg 8 + mem(5) $end
$var reg 8 , mem(6) $end
$var reg 8 - mem(7) $end
$var reg 8 . mem(8) $end
$var reg 8 / mem(9) $end
$var reg 8 0 mem(10) $end
$var reg 8 1 mem(11) $end
$var reg 8 2 mem(12) $end
$var reg 8 3 mem(13) $end
$var reg 8 4 mem(14) $end
$var reg 8 5 mem(15) $end
$var reg 8 6 mem(16) $end
$var reg 8 7 mem(17) $end
$var reg 8 8 mem(18) $end
$var reg 8 9 mem(19) $end
$var reg 8 : mem(20) $end
$var reg 8 ; mem(21) $end
$var reg 8 < mem(22) $end
$var reg 8 = mem(23) $end
$var reg 8 > mem(24) $end
$var reg 8 ? mem(25) $end
$var reg 8 @ mem(26) $end
$var reg 8 A mem(27) $end
$var reg 8 B mem(28) $end
$var reg 8 C mem(29) $end
$var reg 8 D mem(30) $end
$var reg 8 E mem(31) $end
$upscope $end
$upscope $end
$upscope $end

$enddefinitions $end
$dumpvars
b00000000 !
b00000 "
0#
b00000000 $
0%
b00000000 &
b00000000 '
b00000000 (
b00000000 )
b00000000 *
b00000000 +
b00000000 ,
b00000000 -
b00000000 .
b00000000 /
b00000000 0
b00000000 1
b00000000 2
b00000000 3
b00000000 4
b00000000 5
b00000000 6
b00000000 7
b00000000 8
b00000000 9
b00000000 :
b00000000 ;
b00000000 <
b00000000 =
b00000000 >
b00000000 ?
b00000000 @
b00000000 A
b00000000 B
b00000000 C
b00000000 D
b00000000 E
$end
#5
1%
#10
1#
#20
0#
b10100001 $
b01011 "
#30
1#
b10100001 1
b10100001 !
#40
0#
b00011000 $
b00001 "
b00000000 !
#50
1#
b00011000 '
b00011000 !
#60
0#
b00000000 $
#69
0%
#70
1#
#80
0#
b10000000 $
b00011 "
b00000000 !
#90
1#
#99
1%
#100
0#
b10111011 $
b11100 "
#110
1#
b10111011 B
b10111011 !
#120
0#
b01011010 $
b10101 "
b00000000 !
#130
1#
b01011010 ;
b01011010 !
#134
0%
#140
0#
b00001011 $
b10011 "
b00000000 !
#150
1#
#157
1%
#160
0#
b01001101 $
b01011 "
b10100001 !
#170
1#
b01001101 1
b01001101 !
#180
0#
b11000010 $
b10010 "
b00000000 !
#190
1#
b11000010 8
b11000010 !
#200
0#
b01011011 $
b11111 "
b00000000 !
#210
1#
b01011011 E
b01011011 !
#212
0%
#220
0#
b01000000 $
b10000 "
b00000000 !
#230
1#
#237
1%
#240
0#
b01101000 $
b00011 "
#250
1#
b01101000 )
b01101000 !
#260
0#
b11100010 $
b01100 "
b00000000 !
#270
1#
b11100010 2
b11100010 !
#280
0#
b00101110 $
b11010 "
b00000000 !
#287
0%
#290
1#
#300
0#
b10101000 $
b10010 "
b11000010 !
#310
1#
#315
1%
#320
0#
b11101101 $
b11011 "
b00000000 !
#330
1#
b11101101 A
b11101101 !
#340
0#
b00110000 $
b00001 "
b00011000 !
#350
1#
b00110000 '
b00110000 !
#360
0#
b01010111 $
b11110 "
b00000000 !
#367
0%
#370
1#
#380
0#
b10001000 $
b10110 "
#390
1#
#394
1%
#400
0#
b10001010 $
b11101 "
#410
1#
b10001010 C
b10001010 !
#420
0#
b11000000 $
b01100 "
b11100010 !
#430
1#
b11000000 2
b11000000 !
#433
0%
#440
0#
b10100101 $
b00000 "
b00000000 !
#450
1#
#457
1%
#460
0#
b10110001 $
b01111 "
#470
1#
b10110001 5
b10110001 !
#480
0#
b00010001 $
b01100 "
b11000000 !
#490
1#
b00010001 2
b00010001 !
#500
0#
b10100111 $
#510
1#
b10100111 2
b10100111 !
#514
0%
#520
0#
b00000001 $
b11011 "
b11101101 !
#530
1#
#540
0#
b00000000 $
b01100 "
b10100111 !
#546
1%
#550
1#
b00000000 2
b00000000 !
#560
0#
b10101000 $
#570
1#
b10101000 2
b10101000 !
#580
0#
b10000110 $
b11001 "
b00000000 !
#590
1#
b10000110 ?
b10000110 !
#600
0#
b00000011 $
b11011 "
b11101101 !
#605
0%
#610
1#
#620
0#
b11010010 $
b10001 "
b00000000 !
#630
1#
#639
1%
#640
0#
b01011011 $
b10011 "
#650
1#
b01011011 9
b01011011 !
#660
0#
b11110001 $
b00101 "
b00000000 !
#670
1#
b11110001 +
b11110001 !
#680
0#
b00000101 $
b00011 "
b01101000 !
#690
1#
b00000101 )
b00000101 !
#692
0%
#700
0#
b10100011 $
b01100 "
b10101000 !
#710
1#
#715
1%
#720
0#
b00001101 $
b01001 "
b00000000 !
#730
1#
b00001101 /
b00001101 !
#740
0#
b01110101 $
b01100 "
b10101000 !
#750
1#
0%
#760
0#
b10111010 $
b00101 "
b11110001 !
#770
1#
#778
1%
#780
0#
b01001100 $
b10100 "
b00000000 !
#790
1#
b01001100 :
b01001100 !
#800
0#
b11100000 $
b01101 "
b00000000 !
#810
1#
b11100000 3
b11100000 !
#820
0#
b01011101 $
b10110 "
b00000000 !
#830
1#
b01011101 <
b01011101 !
#836
0%
#840
0#
b01110101 $
b11001 "
b10000110 !
#850
1#
#860
0#
1%
b01110011 $
b00111 "
b00000000 !
#870
1#
b01110011 -
b01110011 !
#880
0#
b00011010 $
b10110 "
b01011101 !
#890
1#
b00011010 <
b00011010 !
#900
0#
b00100010 $
b01010 "
b00000000 !
#910
1#
b00100010 0
b00100010 !
#914
0%
#920
0#
b00010000 $
b10001 "
b00000000 !
#930
1#
#940
0#
b10100011 $
b01011 "
b01001101 !
#945
1%
#950
1#
b10100011 1
b10100011 !
#960
0#
b11101001 $
b11000 "
b00000000 !
#970
1#
b11101001 >
b11101001 !
#977
0%
#980
0#
b11101111 $
b01110 "
b00000000 !
#990
1#
#1000
0#
b10101000 $
b00000 "
#1005
1%
#1010
1#
b10101000 &
b10101000 !
#1020
0#
b11010010 $
b00001 "
b00110000 !
#1030
1#
b11010010 '
b11010010 !
#1040
0#
b10100100 $
#1042
0%
#1050
1#
#1060
0#
b10000101 $
b10100 "
b01001100 !
#1065
1%
#1070
1#
b10000101 :
b10000101 !
#1080
0#
b00101110 $
b11011 "
b11101101 !
#1090
1#
b00101110 A
b00101110 !
#1100
0#
b01101111 $
b11111 "
b01011011 !
#1107
0%
#1110
1#
#1120
0#
b00001011 $
b01000 "
b00000000 !
#1130
1#
#1135
1%
#1140
0#
b00001001 $
b01111 "
b10110001 !
#1150
1#
b00001001 5
b00001001 !
#1160
0#
b00110010 $
b11101 "
b10001010 !
#1170
1#
b00110010 C
b00110010 !
#1175
0%
#1180
0#
b01110100 $
b01100 "
b10101000 !
#1190
1#
#1198
1%
#1200
0#
b01001110 $
b10000 "
b00000000 !
#1210
1#
b01001110 6
b01001110 !
#1220
0#
b10100110 $
#1229
0%
#1230
1#
#1240
0#
b10110101 $
b11001 "
b10000110 !
#1250
1#
#1260
0#
b00110111 $
b00000 "
b10101000 !
#1263
1%
#1270
1#
b00110111 &
b00110111 !
#1280
0#
b10001000 $
b01101 "
b11100000 !
#1290
1#
b10001000 3
b10001000 !
#1293
0%
#1300
0#
b10110001 $
b11110 "
b00000000 !
#1310
1#
#1313
1%
#1320
0#
b01110110 $
b01010 "
b00100010 !
#1330
1#
b01110110 0
b01110110 !
#1340
0#
b00110111 $
b11011 "
b00101110 !
#1350
1#
b00110111 A
b00110111 !
#1354
0%
#1360
0#
b10111110 $
b01010 "
b01110110 !
#1370
1#
#1380
0#
b01101010 $
#1381
1%
#1390
1#
b01101010 0
b01101010 !
#1400
0#
b00011111 $
b00110 "
b00000000 !
#1410
1#
b00011111 ,
b00011111 !
#1420
0#
b00110010 $
b11111 "
b01011011 !
#1422
0%
#1430
1#
#1440
0#
b01011011 $
b00010 "
b00000000 !
#1446
1%
#1450
1#
b01011011 (
b01011011 !
#1460
0#
b00110110 $
b11111 "
#1470
1#
b00110110 E
b00110110 !
#1478
0%
#1480
0#
b00111001 $
b10001 "
b00000000 !
#1490
1#
#1499
1%
#1500
0#
b00000001 $
b00000 "
b00110111 !
#1510
1#
b00000001 &
b00000001 !
#1520
0#
b01011011 $
b01100 "
b10101000 !
#1530
1#
b01011011 2
b01011011 !
#1540
0#
b01001001 $
b00011 "
b00000101 !
#1542
0%
#1550
1#
#1560
0#
b00011011 $
b11001 "
b10000110 !
#1570
1#
#1573
1%
#1580
0#
b00101001 $
b11010 "
b00000000 !
#1590
1#
b00101001 @
b00101001 !
#1600
0#
b10001100 $
b00100 "
b00000000 !
#1610
1#
b10001100 *
b10001100 !
#1616
0%
#1620
0#
b10010100 $
b11010 "
b00101001 !
#1630
1#
#1640
0#
1%
b11001111 $
b01110 "
b00000000 !
#1650
1#
b11001111 4
b11001111 !
#1660
0#
b01000001 $
b11111 "
b00110110 !
#1670
1#
b01000001 E
b01000001 !
#1676
0%
#1680
0#
b01011111 $
b00101 "
b11110001 !
#1690
1#
#1700
0#
b10100100 $
b01001 "
b00001101 !
#1710
1#
1%
b10100100 /
b10100100 !
#1720
0#
b00111001 $
b11001 "
b10000110 !
#1730
1#
b00111001 ?
b00111001 !
#1740
0#
b11011001 $
b01111 "
b00001001 !
#1750
1#
b11011001 5
b11011001 !
#1760
0#
0%
b00110011 $
b01010 "
b01101010 !
#1770
1#
#1780
0#
b01010111 $
b01101 "
b10001000 !
#1787
1%
#1790
1#
b01010111 3
b01010111 !
#1800
0#
b10110101 $
b00010 "
b01011011 !
#1810
1#
b10110101 (
b10110101 !
#1820
0#
b01100110 $
b10100 "
b10000101 !
#1830
1#
b01100110 :
b01100110 !
#1840
0#
b11111100 $
b00101 "
b11110001 !
#1848
0%
#1850
1#
#1860
0#
b10010000 $
b11000 "
b11101001 !
#1870
1#
#1879
1%
#1880
0#
b11010110 $
b10111 "
b00000000 !
#1890
1#
b11010110 =
b11010110 !
#1900
0#
b10000110 $
b11001 "
b00111001 !
#1910
1#
b10000110 ?
b10000110 !
#1920
0#
b01000111 $
b00010 "
b10110101 !
#1930
1#
b01000111 (
b01000111 !
#1939
0%
#1940
0#
b01000000 $
b11000 "
b11101001 !
#1950
1#
#1960
0#
b10011010 $
b00101 "
b11110001 !
#1964
1%
#1970
1#
b10011010 +
b10011010 !
#1980
0#
b10000101 $
b11101 "
b00110010 !
#1990
1#
b10000101 C
b10000101 !
#2000
0#
b00111100 $
b10000 "
b01001110 !
#2010
1#
b00111100 6
b00111100 !
#2020
0#
b11101110 $
b10001 "
b00000000 !
#2021
0%
#2030
1#
#2040
0#
b00111111 $
b01110 "
b11001111 !
#2050
1#
#2053
1%
#2060
0#
b11101111 $
b10100 "
b01100110 !
#2070
1#
b11101111 :
b11101111 !
#2080
0#
b01100000 $
b00111 "
b01110011 !
#2090
1#
b01100000 -
b01100000 !
#2098
0%
#2100
0#
b01110101 $
b11011 "
b00110111 !
#2110
1#
#2120
0#
b10010101 $
b00011 "
b00000101 !
#2129
1%
#2130
1#
b10010101 )
b10010101 !
#2140
0#
b00001100 $
b11101 "
b10000101 !
#2150
1#
b00001100 C
b00001100 !
#2160
0#
b11001101 $
b01011 "
b10100011 !
#2170
1#
b11001101 1
b11001101 !
#2172
0%
#2180
0#
b00010101 $
b10111 "
b11010110 !
#2190
1#
#2200
0#
b01011010 $
b11100 "
b10111011 !
#2204
1%
#2210
1#
b01011010 B
b01011010 !
#2220
0#
b11000011 $
b01011 "
b11001101 !
#2230
1#
b11000011 1
b11000011 !
#2240
0#
b00101010 $
b00100 "
b10001100 !
#2247
0%
#2250
1#
#2260
0#
b11000001 $
b11010 "
b00101001 !
#2270
1#
#2275
1%
#2280
0#
b11100001 $
b11101 "
b00001100 !
#2290
1#
b11100001 C
b11100001 !
#2300
0#
b01001010 $
b11100 "
b01011010 !
#2310
1#
b01001010 B
b01001010 !
#2320
0#
b00011101 $
b10010 "
b11000010 !
#2330
1#
b00011101 8
b00011101 !
#2336
0%
#2340
0#
b10001110 $
b11010 "
b00101001 !
#2350
1#
#2360
0#
b00000111 $
b00101 "
b10011010 !
#2361
1%
#2370
1#
b00000111 +
b00000111 !
#2380
0#
b00100001 $
b11110 "
b00000000 !
#2390
1#
b00100001 D
b00100001 !
#2400
0#
b00011101 $
b01011 "
b11000011 !
#2410
1#
b00011101 1
b00011101 !
#2415
0%
#2420
0#
b10000000 $
b10000 "
b00111100 !
#2430
1#
#2437
1%
#2440
0#
b11000100 $
b11100 "
b01001010 !
#2450
1#
b11000100 B
b11000100 !
#2460
0#
b00101110 $
b01011 "
b00011101 !
#2470
1#
b00101110 1
b00101110 !
#2475
0%
#2480
0#
b10111110 $
b00101 "
b00000111 !
#2490
1#
#2500
0#
b11110110 $
b11111 "
b01000001 !
#2505
1%
#2510
1#
b11110110 E
b11110110 !
#2520
0#
b00010000 $
b00110 "
b00011111 !
#2530
1#
b00010000 ,
b00010000 !
#2536
0%
#2540
0#
b10111101 $
b11110 "
b00100001 !
#2550
1#
#2559
1%
#2560
0#
b10011011 $
b10100 "
b11101111 !
#2570
1#
b10011011 :
b10011011 !
#2580
0#
b10000010 $
#2590
1#
b10000010 :
b10000010 !
#2600
0#
b00011001 $
b01000 "
b00000000 !
#2603
0%
#2610
1#
#2620
0#
b11111111 $
b00101 "
b00000111 !
#2630
1#
1%
b11111111 +
b11111111 !
#2640
0#
b00000000 $
b11111 "
b11110110 !
#2650
1#
b00000000 E
b00000000 !
#2660
0#
b10111100 $
b00100 "
b10001100 !
#2667
0%
#2670
1#
#2680
0#
b11110010 $
b01100 "
b01011011 !
#2687
1%
#2690
1#
b11110010 2
b11110010 !
#2700
0#
b01000000 $
b01010 "
b01101010 !
#2710
1#
b01000000 0
b01000000 !
#2720
0#
b11000101 $
b01001 "
b10100100 !
#2730
1#
b11000101 /
b11000101 !
#2739
0%
#2740
0#
b00100101 $
b11000 "
b11101001 !
#2750
1#
#2760
0#
b01000011 $
b10011 "
b01011011 !
#2769
1%
#2770
1#
b01000011 9
b01000011 !
#2780
0#
b10011001 $
b00101 "
b11111111 !
#2790
1#
b10011001 +
b10011001 !
#2800
0#
b01100101 $
b10001 "
b00000000 !
#2810
1#
b01100101 7
b01100101 !
#2814
0%
#2820
0#
b00110101 $
b00011 "
b10010101 !
#2830
1#
#2835
1%
#2840
0#
b11001110 $
b00010 "
b01000111 !
#2850
1#
b11001110 (
b11001110 !
#2860
0#
b10101001 $
b10011 "
b01000011 !
#2870
1#
b10101001 9
b10101001 !
#2876
0%
#2880
0#
b01011101 $
b11100 "
b11000100 !
#2890
1#
#2900
0#
b01101011 $
b10101 "
b01011010 !
#2903
1%
#2910
1#
b01101011 ;
b01101011 !
#2920
0#
b00010001 $
b11100 "
b11000100 !
#2930
1#
b00010001 B
b00010001 !
#2935
0%
#2940
0#
b10001111 $
b00110 "
b00010000 !
#2950
1#
#2960
0#
b10110000 $
b10001 "
b01100101 !
#2966
1%
#2970
1#
b10110000 7
b10110000 !
#2980
0#
b01101010 $
b11010 "
b00101001 !
#2990
1#
b01101010 @
b01101010 !
#3000
0#
b01010101 $
b01011 "
b00101110 !
#3010
1#
b01010101 1
b01010101 !
#3013
0%
#3020
0#
b10100010 $
b01001 "
b11000101 !
#3030
1#
#3039
1%
#3040
0#
b10001101 $
b00001 "
b11010010 !
#3050
1#
b10001101 '
b10001101 !
#3060
0#
b11011101 $
b11100 "
b00010001 !
#3070
1#
b11011101 B
b11011101 !
#3080
0#
b10110111 $
b01110 "
b11001111 !
#3090
1#
b10110111 4
b10110111 !
#3096
0%
#3100
0#
b01000011 $
b00101 "
b10011001 !
#3110
1#
#3117
1%
#3120
0#
b11110101 $
b00011 "
b10010101 !
#3130
1#
b11110101 )
b11110101 !
#3140
0#
b10010001 $
b01010 "
b01000000 !
#3150
1#
b10010001 0
b10010001 !
#3160
0#
b10000100 $
b11000 "
b11101001 !
#3169
0%
#3170
1#
#3180
0#
b00001001 $
b10101 "
b01101011 !
#3190
1#
#3197
1%
#3200
0#
b11100010 $
b01100 "
b11110010 !
#3210
1#
b11100010 2
b11100010 !
#3220
0#
b01110101 $
b10101 "
b01101011 !
#3230
1#
b01110101 ;
b01110101 !
#3240
0#
b11000110 $
b00001 "
b10001101 !
#3246
0%
#3250
1#
#3260
0#
b00011100 $
b11100 "
b11011101 !
#3268
1%
#3270
1#
b00011100 B
b00011100 !
#3280
0#
b11011011 $
b00100 "
b10001100 !
#3290
1#
b11011011 *
b11011011 !
#3300
0#
b00101110 $
b11111 "
b00000000 !
#3310
1#
b00101110 E
b00101110 !
#3320
0#
b10101101 $
b10111 "
b11010110 !
#3330
1#
b10101101 =
b10101101 !
#3331
0%
#3340
0#
b00000101 $
b10001 "
b10110000 !
#3350
1#
#3355
1%
#3360
0#
b00010111 $
b10110 "
b00011010 !
#3370
1#
b00010111 <
b00010111 !
#3380
0#
b00101101 $
b01100 "
b11100010 !
#3390
1#
b00101101 2
b00101101 !
#3400
0#
b01110001 $
b10111 "
b10101101 !
#3410
1#
b01110001 =
b01110001 !
#3414
0%
#3420
0#
b10001001 $
b11100 "
b00011100 !
#3430
1#
#3439
1%
#3440
0#
b01010111 $
b11000 "
b11101001 !
#3450
1#
b01010111 >
b01010111 !
#3460
0#
b00100011 $
b00011 "
b11110101 !
#3470
1#
b00100011 )
b00100011 !
#3480
0#
b10001010 $
b11000 "
b01010111 !
#3490
1#
b10001010 >
b10001010 !
#3492
0%
#3500
0#
b01110111 $
b01010 "
b10010001 !
#3510
1#
#3520
0#
b00011010 $
b01110 "
b10110111 !
#3522
1%
#3530
1#
b00011010 4
b00011010 !
#3540
0#
b11010100 $
b01001 "
b11000101 !
#3550
1#
b11010100 /
b11010100 !
#3555
0%
#3560
0#
b01100010 $
b00110 "
b00010000 !
#3570
1#
#3580
0#
b00101110 $
b00000 "
b00000001 !
#3583
1%
#3590
1#
b00101110 &
b00101110 !
#3600
0#
b11001110 $
b01010 "
b10010001 !
#3610
1#
b11001110 0
b11001110 !
#3620
0#
b11100001 $
b10001 "
b10110000 !
#3630
1#
b11100001 7
b11100001 !
#3639
0%
#3640
0#
b10011010 $
b10111 "
b01110001 !
#3650
1#
#3660
0#
b00011100 $
b10000 "
b00111100 !
#3670
1#
#3672
1%
#3680
0#
b01001011 $
b01010 "
b11001110 !
#3690
1#
b01001011 0
b01001011 !
#3700
0#
b10101000 $
b11001 "
b10000110 !
#3710
1#
0%
#3720
0#
b10000010 $
b00100 "
b11011011 !
#3730
1#
1%
b10000010 *
b10000010 !
#3740
0#
b01110001 $
b11000 "
b10001010 !
#3750
1#
b01110001 >
b01110001 !
#3760
0#
b01010101 $
b01110 "
b00011010 !
#3770
1#
b01010101 4
b01010101 !
#3780
0#
b11001001 $
b11101 "
b11100001 !
#3781
0%
#3790
1#
#3800
0#
b11001110 $
b00111 "
b01100000 !
#3810
1#
1%
b11001110 -
b11001110 !
#3820
0#
b10110000 $
b10011 "
b10101001 !
#3830
1#
b10110000 9
b10110000 !
#3840
0#
b11101100 $
b10101 "
b01110101 !
#3841
0%
#3850
1#
#3860
0#
b10110101 $
b10110 "
b00010111 !
#3862
1%
#3870
1#
b10110101 <
b10110101 !
#3880
0#
b11011111 $
b00001 "
b10001101 !
#3890
1#
b11011111 '
b11011111 !
#3898
0%
#3900
0#
b00000111 $
b11111 "
b00101110 !
#3910
1#
#3920
0#
b10010001 $
b10110 "
b10110101 !
#3923
1%
#3930
1#
b10010001 <
b10010001 !
#3940
0#
b01111101 $
b11011 "
b00110111 !
#3950
1#
b01111101 A
b01111101 !
#3958
0%
#3960
0#
b11111010 $
b01110 "
b01010101 !
#3970
1#
#3980
0#
b00101011 $
b00000 "
b00101110 !
#3987
1%
#3990
1#
b00101011 &
b00101011 !
#4000
0#
b01110101 $
b00001 "
b11011111 !
