32-Bit DRegister/DRegister_32Bit.v
// File: DRegister_32Bit.v
// Generated by MyHDL 0.11.45
// Date: Thu Jun 27 12:50:13 2024


`timescale 1ns/10ps

module DRegister_32Bit (
    clk,
    rst,
    load,
    par_in,
    par_out
);
// Simple 32-bit data register. It can load and reset.
// :param clk: Clock signal
// :param rst: Reset signal
// :param load: Load enable signal
// :param par_in: Parallel 32-bit input
// :param par_out: Parallel 32-bit output

input clk;
input rst;
input load;
input [31:0] par_in;
output [31:0] par_out;
reg [31:0] par_out;




always @(posedge clk, negedge rst) begin: DREGISTER_32BIT_LOGIC
    if (rst == 0) begin
        par_out <= 0;
    end
    else begin
        if (load) begin
            par_out <= par_in;
        end
    end
end

endmodule

32-Bit DRegister/DRegister_32Bit.vcd
$date
    Thu Jun 27 12:50:13 2024
$end
$version
    MyHDL 0.11.45
$end
$timescale
    1ns
$end

$scope module DRegister_32Bit $end
$var reg 32 ! par_out $end
$var reg 1 " clk $end
$var reg 1 # load $end
$var reg 32 $ par_in $end
$var reg 1 % rst $end
$scope module Register0 $end
$var reg 1 " clk $end
$var reg 1 % rst $end
$var reg 1 # load $end
$var reg 32 $ par_in $end
$var reg 32 ! par_out $end
$upscope $end
$upscope $end

$enddefinitions $end
$dumpvars
b00000000000000000000000000000000 !
0"
0#
b00000000000000000000000000000000 $
0%
$end
#5
1%
1#
#10
1"
#20
0"
b11101110010100111010010010000011 $
#30
1"
b11101110010100111010010010000011 !
#40
0"
b00110011010000100110100100110110 $
#45
0#
#50
1"
#60
0"
b10001111010111000100000110101011 $
#70
1"
#74
1#
#80
0"
b10000111100110110100010010111010 $
#90
1"
b10000111100110110100010010111010 !
#100
0"
b01111000000110100010100111011000 $
#104
0#
#110
1"
#120
0"
b00011100111101110111000111010011 $
#130
1"
#135
1#
#140
0"
b10010010001110101110101010010011 $
#150
1"
b10010010001110101110101010010011 !
#160
0"
b01111001110110011111001000010011 $
#170
1"
b01111001110110011111001000010011 !
#180
0"
b01111001101110010001111010010111 $
#182
0#
#190
1"
#200
0"
b00011010101001001101101100101010 $
#210
1"
1#
b00011010101001001101101100101010 !
#220
0"
b00000111111101100010110100011110 $
#230
1"
b00000111111101100010110100011110 !
#240
0"
b10010100011011010001100001011011 $
#250
1"
b10010100011011010001100001011011 !
#256
0#
#260
0"
b11110000100011101001100101010010 $
#270
1"
#278
1#
#280
0"
b00110011011000100011111000011010 $
#290
1"
b00110011011000100011111000011010 !
#300
0"
b11101001110001001101101110101110 $
#310
1"
b11101001110001001101101110101110 !
#320
0"
b01100100000110000110000111010100 $
#330
1"
b01100100000110000110000111010100 !
#337
0#
#340
0"
b11000010111010110111101011101011 $
#350
1"
#360
0"
b00001111100110100100000111101111 $
#366
1#
#370
1"
b00001111100110100100000111101111 !
#380
0"
b10111110001100110010011010000101 $
#390
1"
b10111110001100110010011010000101 !
#400
0"
b00000000010101010100110111100110 $
#410
1"
b00000000010101010100110111100110 !
#420
0"
b00010001000100110000111101100010 $
#427
0#
#430
1"
#440
0"
b00010010110000001001111001111011 $
#450
1"
#455
1#
#458
0%
b00000000000000000000000000000000 !
#460
0"
b10101110110110110111010010000011 $
#470
1"
#480
0"
b01101101111110000110011110001000 $
#490
1"
#500
0"
b11011011010011101100111010111111 $
#510
1"
#517
0#
#520
0"
b00000001000110110101000100010100 $
#530
1"
#540
0"
b10101100011101000101100001111000 $
#550
1"
1#
#560
0"
b01100010101100010011000011100110 $
#570
1"
#580
0"
b00111001001010010001101011110000 $
#590
1"
0#
#600
0"
b11101100101010011110001011101101 $
#610
1"
#613
1#
#620
0"
b11011010011100001111000001111000 $
#630
1"
#640
0"
b00111010011100111001001000100100 $
#650
1"
#660
0"
b00000111100000110100011110010010 $
#668
0#
#670
1"
#680
0"
b11010110010001110101000010000001 $
#690
1"
#700
0"
b01001001110111100111110100011111 $
#701
1#
#710
1"
#720
0"
b00100000011010000101011011000111 $
#730
1"
#740
0"
b01111000100101110100001010011101 $
#750
1"
#760
0"
b00111100010100011111000001101111 $
#762
0#
#770
1"
#779
1%
#780
0"
b00110111101111000110011101101100 $
#785
1#
#790
1"
b00110111101111000110011101101100 !
#800
0"
b00101110010000010110011010110011 $
#810
1"
b00101110010000010110011010110011 !
#820
0"
b11111110101011000101110000100100 $
#830
1"
b11111110101011000101110000100100 !
#832
0#
#840
0"
b11001111101110101000010100010111 $
#850
1"
#860
0"
b00111000000011101000111110001100 $
#863
1#
#870
1"
b00111000000011101000111110001100 !
#880
0"
b10001111010111001111010011001010 $
#890
1"
b10001111010111001111010011001010 !
#900
0"
b10010001101011000011100111010000 $
#910
1"
b10010001101011000011100111010000 !
#915
0#
#920
0"
b10110101010010011011000110111000 $
#930
1"
#940
0"
1#
b11000001001100100101000001101101 $
#950
1"
b11000001001100100101000001101101 !
#960
0"
b10101000001000011000110011100101 $
#970
1"
b10101000001000011000110011100101 !
#980
0"
b01111001011111110001100101000011 $
#990
1"
b01111001011111110001100101000011 !
#1000
0"
b00000010100010010001011101001101 $
#1001
0#
#1010
1"
#1020
0"
b10001110111010001111010011100110 $
#1030
1"
#1032
1#
#1040
0"
b00011101001110011000111111001111 $
#1050
1"
b00011101001110011000111111001111 !
#1060
0"
b01101110111000011110011100010010 $
#1070
1"
b01101110111000011110011100010010 !
#1080
0"
b11001001111110111010100010010001 $
#1087
0#
#1090
1"
#1100
0"
b01111111011111110110110001100011 $
#1110
1"
#1118
1#
#1120
0"
b01010010100101010011101011001010 $
#1130
1"
b01010010100101010011101011001010 !
#1140
0"
b11000001101111000010101000011110 $
#1149
0#
#1150
1"
#1160
0"
b10111001011111100000011010001111 $
#1170
1"
#1172
1#
#1180
0"
b11101110000100100101111111010110 $
#1190
1"
b11101110000100100101111111010110 !
#1200
0"
b10111110010111001001101110101110 $
#1210
1"
b10111110010111001001101110101110 !
#1217
0#
#1220
0"
b11000110111000110001111010000010 $
#1230
1"
#1239
1#
#1240
0"
b11001000111111001110110100100100 $
#1250
1"
b11001000111111001110110100100100 !
#1260
0"
b01111100111001101111101100010011 $
#1270
1"
0#
#1280
0"
b10010100101100111101001101111111 $
#1290
1"
#1293
1#
#1300
0"
b11110100111110011110111001101110 $
#1310
1"
b11110100111110011110111001101110 !
#1320
0"
b01010000001011001011011101100110 $
#1328
0%
b00000000000000000000000000000000 !
#1330
1"
#1340
0"
b10111101001110001101001110110010 $
#1341
0#
#1350
1"
#1360
0"
b01011000011010011000110111000100 $
#1370
1"
#1372
1#
#1380
0"
b00100000101100100101101111101110 $
#1390
1"
#1400
0"
b00000100001100101001010111011110 $
#1410
1"
#1417
0#
#1420
0"
b00111111000111100100110001001100 $
#1430
1"
#1439
1#
#1440
0"
b01100000000110001101100011100011 $
#1450
1"
#1460
0"
b00110101010100111001010001110100 $
#1470
1"
#1479
0#
#1480
0"
b11010100110100111111101101000100 $
#1490
1"
#1500
0"
b00011100001011000111111001000000 $
#1510
1"
#1513
1#
#1520
0"
b01011000000101010110111101110010 $
#1530
1"
#1540
0"
b10100001100001100110001010010100 $
#1550
1"
#1560
0"
b01111011110011010110001010010001 $
#1570
1"
#1571
0#
#1580
0"
b11000101100100001001000110110001 $
#1590
1"
#1600
0"
b00101011011010010001010001011101 $
#1605
1#
#1610
1"
#1620
0"
b00000001101000000011000110100010 $
#1630
1"
#1640
0"
b11001001001001111000110101001100 $
#1643
1%
#1650
1"
b11001001001001111000110101001100 !
#1660
0"
b11100001100101001000111101011110 $
#1664
0#
#1670
1"
#1680
0"
b10100011110001101111011111100110 $
#1685
1#
#1690
1"
b10100011110001101111011111100110 !
#1700
0"
b01001000000111110111110100111101 $
#1710
1"
b01001000000111110111110100111101 !
#1717
0#
#1720
0"
b11001101101000110000101111001111 $
#1730
1"
#1737
1#
#1740
0"
b00011011000010101010011101011000 $
#1750
1"
b00011011000010101010011101011000 !
#1760
0"
b10100110111101110110101111110001 $
#1770
1"
b10100110111101110110101111110001 !
#1780
0"
b10000010000111101101000100101011 $
#1781
0#
#1790
1"
#1800
0"
b10000110110010100101010010011111 $
#1810
1"
#1811
1#
#1820
0"
b00111000100000011010100000011100 $
#1830
1"
b00111000100000011010100000011100 !
#1840
0"
b10011111000001100100001111100011 $
#1850
1"
b10011111000001100100001111100011 !
#1853
0#
#1860
0"
b11100110011011010001111010001010 $
#1870
1"
#1880
0"
1#
b01000101111011110110000001010110 $
#1890
1"
b01000101111011110110000001010110 !
#1900
0"
b11100001111100011100000001001101 $
#1910
1"
b11100001111100011100000001001101 !
#1920
0"
b10001110001010101001001100010010 $
#1930
1"
b10001110001010101001001100010010 !
#1938
0#
#1940
0"
b00110110001110110110111000010111 $
#1950
1"
#1960
0"
1#
b01011000110101010110001100110011 $
#1970
1"
b01011000110101010110001100110011 !
#1980
0"
b11000010011000100111100001111011 $
#1990
1"
b11000010011000100111100001111011 !
#2000
0"
b10000000010101000101010010101000 $
